Metadata-Version: 2.1
Name: moduledk
Version: 0.0.1
Summary: add func
Home-page: https://github.com/ModuledkQuy/test
Author: moduledk
Author-email: moduledk@example.com
License: UNKNOWN
Platform: UNKNOWN
